LICENSE
MANIFEST.in
README.md
requirements.txt
setup.py
tox.ini
django_resizer.egg-info/PKG-INFO
django_resizer.egg-info/SOURCES.txt
django_resizer.egg-info/dependency_links.txt
django_resizer.egg-info/requires.txt
django_resizer.egg-info/top_level.txt
resizer/__init__.py
resizer/models.py
resizer/tests.py
resizer/views.py