Metadata-Version: 1.0
Name: django-resizer
Version: 1.0
Summary: A Django app for fetching resized and/or cropped images through a url.
Home-page: https://bitbucket.org/nextscreenlabs/django-resizer
Author: Jason Christa
Author-email: jason@zeitcode.com
License: UNKNOWN
Platform: UNKNOWN
Classifier: Environment :: Web Environment
Classifier: License :: OSI Approved :: BSD License
Classifier: Framework :: Django
Classifier: Programming Language :: Python
